clusterp
