Metadata-Version: 1.2
Name: clusterp
Version: 0.1.4
Summary: Clusterp : Cluster profiling made easy
Home-page: https://github.com/abdelkafiahmed/clusterp
Author: Ahmed Abdelkafi
Author-email: abdelkafiahmed@yahoo.fr
Maintainer: Ahmed Abdelkafi
Maintainer-email: abdelkafiahmed@yahoo.fr
License: Apache License Version 2.0
Download-URL: https://github.com/abdelkafiahmed/clusterp/archive/0.1.4.tar.gz
Platform: ALL
Classifier: Development Status :: 5 - Production/Stable
Classifier: Environment :: Console
Classifier: Intended Audience :: Developers
Classifier: Intended Audience :: System Administrators
Classifier: License :: OSI Approved :: Apache Software License
Classifier: Operating System :: MacOS :: MacOS X
Classifier: Operating System :: Unix
Classifier: Operating System :: POSIX
Classifier: Programming Language :: Python
Classifier: Programming Language :: Python :: 2 :: Only
Classifier: Programming Language :: Python :: 2.5
Classifier: Programming Language :: Python :: 2.6
Classifier: Programming Language :: Python :: 2.7
Classifier: Topic :: Software Development
Classifier: Topic :: Software Development :: Build Tools
Classifier: Topic :: Software Development :: Libraries
Classifier: Topic :: Software Development :: Libraries :: Python Modules
Classifier: Topic :: System :: Clustering
Classifier: Topic :: System :: Software Distribution
Classifier: Topic :: System :: Systems Administration
